README.rst
codevalidator.py
setup.py
codevalidator.egg-info/PKG-INFO
codevalidator.egg-info/SOURCES.txt
codevalidator.egg-info/dependency_links.txt
codevalidator.egg-info/entry_points.txt
codevalidator.egg-info/requires.txt
codevalidator.egg-info/top_level.txt
pythontidy/PythonTidy.py
pythontidy/__init__.py
test/test.py