Metadata-Version: 1.1
Name: codevalidator
Version: 0.8.1
Summary: Simple source code validator with file reformatting option (remove trailing WS, pretty print XML, ..)
Home-page: https://github.com/hjacobs/codevalidator
Author: Henning Jacobs
Author-email: henning@jacobs1.de
License: UNKNOWN
Keywords: formatter,beautify,indentation
Platform: UNKNOWN
Classifier: Development Status :: 3 - Alpha
Classifier: Environment :: Console
Classifier: Intended Audience :: Developers
Classifier: Topic :: Software Development :: Pre-processors
Classifier: Topic :: Text Processing :: Markup :: XML
Classifier: Programming Language :: Python :: 2.7
